geometric_graphs/__init__.py
geometric_graphs/__main__.py
geometric_graphs/api.py
geometric_graphs/cli.py
geometric_graphs/generators.py
geometric_graphs/util.py
geometric_graphs/version.py
geometric_graphs-0.0.3.dist-info/LICENSE
geometric_graphs-0.0.3.dist-info/METADATA
geometric_graphs-0.0.3.dist-info/WHEEL
geometric_graphs-0.0.3.dist-info/entry_points.txt
geometric_graphs-0.0.3.dist-info/top_level.txt
geometric_graphs-0.0.3.dist-info/RECORD
